telepress/__init__.py
telepress/auth.py
telepress/cli.py
telepress/config.py
telepress/converter.py
telepress/core.py
telepress/exceptions.py
telepress/image_host.py
telepress/interfaces.py
telepress/server.py
telepress/uploader.py
telepress/utils.py
telepress-0.3.5.dist-info/LICENSE
telepress-0.3.5.dist-info/METADATA
telepress-0.3.5.dist-info/WHEEL
telepress-0.3.5.dist-info/entry_points.txt
telepress-0.3.5.dist-info/top_level.txt
telepress-0.3.5.dist-info/RECORD
