Metadata-Version: 2.2
Name: telepress
Version: 0.3.5
Summary: Publish Markdown to Telegraph with external image hosting support
Home-page: https://github.com/zoidberg-xgd/telepress
Author: zoidberg-xgd
Author-email: 
Project-URL: Bug Reports, https://github.com/zoidberg-xgd/telepress/issues
Project-URL: Source, https://github.com/zoidberg-xgd/telepress
Keywords: telegraph,markdown,publishing,image-hosting,imgbb,imgur,r2
Classifier: Development Status :: 4 - Beta
Classifier: Intended Audience :: Developers
Classifier: License :: OSI Approved :: MIT License
Classifier: Programming Language :: Python :: 3
Classifier: Programming Language :: Python :: 3.7
Classifier: Programming Language :: Python :: 3.8
Classifier: Programming Language :: Python :: 3.9
Classifier: Programming Language :: Python :: 3.10
Classifier: Programming Language :: Python :: 3.11
Classifier: Programming Language :: Python :: 3.12
Requires-Python: >=3.7
License-File: LICENSE
Requires-Dist: telegraph
Requires-Dist: markdown
Requires-Dist: requests
Requires-Dist: Pillow
Provides-Extra: api
Requires-Dist: fastapi; extra == "api"
Requires-Dist: uvicorn; extra == "api"
Requires-Dist: python-multipart; extra == "api"
Provides-Extra: dev
Requires-Dist: pytest; extra == "dev"
Requires-Dist: pytest-cov; extra == "dev"
Requires-Dist: httpx; extra == "dev"
Dynamic: author
Dynamic: classifier
Dynamic: description
Dynamic: description-content-type
Dynamic: home-page
Dynamic: keywords
Dynamic: project-url
Dynamic: provides-extra
Dynamic: requires-dist
Dynamic: requires-python
Dynamic: summary
